[
  {
    "ContainingType": "Oracap_App_API.Controllers.PrayersController",
    "Method": "GetPrayers",
    "RelativePath": "api/Prayers",
    "HttpMethod": "GET",
    "IsController": true,
    "Order": 0,
    "Parameters": [],
    "ReturnTypes": [
      {
        "Type": "System.Collections.Generic.IEnumerable\u00601[[Oracap_App_API.Model.PrayerModel, Oracap-App-API, Version=1.0.0.0, Culture=neutral, PublicKeyToken=null]]",
        "MediaTypes": [
          "text/plain",
          "application/json",
          "text/json"
        ],
        "StatusCode": 200
      }
    ]
  },
  {
    "ContainingType": "Oracap_App_API.Controllers.PrayersController",
    "Method": "PostPrayerModel",
    "RelativePath": "api/Prayers",
    "HttpMethod": "POST",
    "IsController": true,
    "Order": 0,
    "Parameters": [
      {
        "Name": "prayerModel",
        "Type": "Oracap_App_API.Model.PrayerModel",
        "IsRequired": true
      }
    ],
    "ReturnTypes": [
      {
        "Type": "Oracap_App_API.Model.PrayerModel",
        "MediaTypes": [
          "text/plain",
          "application/json",
          "text/json"
        ],
        "StatusCode": 200
      }
    ]
  },
  {
    "ContainingType": "Oracap_App_API.Controllers.PrayersController",
    "Method": "GetPrayerModel",
    "RelativePath": "api/Prayers/{id}",
    "HttpMethod": "GET",
    "IsController": true,
    "Order": 0,
    "Parameters": [
      {
        "Name": "id",
        "Type": "System.Int32",
        "IsRequired": true
      }
    ],
    "ReturnTypes": [
      {
        "Type": "Oracap_App_API.Model.PrayerModel",
        "MediaTypes": [
          "text/plain",
          "application/json",
          "text/json"
        ],
        "StatusCode": 200
      }
    ]
  },
  {
    "ContainingType": "Oracap_App_API.Controllers.PrayersController",
    "Method": "PutPrayerModel",
    "RelativePath": "api/Prayers/{id}",
    "HttpMethod": "PUT",
    "IsController": true,
    "Order": 0,
    "Parameters": [
      {
        "Name": "id",
        "Type": "System.Int32",
        "IsRequired": true
      },
      {
        "Name": "prayerModel",
        "Type": "Oracap_App_API.Model.PrayerModel",
        "IsRequired": true
      }
    ],
    "ReturnTypes": []
  },
  {
    "ContainingType": "Oracap_App_API.Controllers.PrayersController",
    "Method": "DeletePrayerModel",
    "RelativePath": "api/Prayers/{id}",
    "HttpMethod": "DELETE",
    "IsController": true,
    "Order": 0,
    "Parameters": [
      {
        "Name": "id",
        "Type": "System.Int32",
        "IsRequired": true
      }
    ],
    "ReturnTypes": []
  },
  {
    "ContainingType": "Oracap_App_API.Controllers.ViewTypesController",
    "Method": "GetViewTypes",
    "RelativePath": "api/ViewTypes",
    "HttpMethod": "GET",
    "IsController": true,
    "Order": 0,
    "Parameters": [],
    "ReturnTypes": [
      {
        "Type": "System.Collections.Generic.IEnumerable\u00601[[Oracap_App_API.Model.ViewTypeModel, Oracap-App-API, Version=1.0.0.0, Culture=neutral, PublicKeyToken=null]]",
        "MediaTypes": [
          "text/plain",
          "application/json",
          "text/json"
        ],
        "StatusCode": 200
      }
    ]
  },
  {
    "ContainingType": "Oracap_App_API.Controllers.ViewTypesController",
    "Method": "PostViewTypeModel",
    "RelativePath": "api/ViewTypes",
    "HttpMethod": "POST",
    "IsController": true,
    "Order": 0,
    "Parameters": [
      {
        "Name": "viewTypeModel",
        "Type": "Oracap_App_API.Model.ViewTypeModel",
        "IsRequired": true
      }
    ],
    "ReturnTypes": [
      {
        "Type": "Oracap_App_API.Model.ViewTypeModel",
        "MediaTypes": [
          "text/plain",
          "application/json",
          "text/json"
        ],
        "StatusCode": 200
      }
    ]
  },
  {
    "ContainingType": "Oracap_App_API.Controllers.ViewTypesController",
    "Method": "GetViewTypeModel",
    "RelativePath": "api/ViewTypes/{id}",
    "HttpMethod": "GET",
    "IsController": true,
    "Order": 0,
    "Parameters": [
      {
        "Name": "id",
        "Type": "System.Int32",
        "IsRequired": true
      }
    ],
    "ReturnTypes": [
      {
        "Type": "Oracap_App_API.Model.ViewTypeModel",
        "MediaTypes": [
          "text/plain",
          "application/json",
          "text/json"
        ],
        "StatusCode": 200
      }
    ]
  },
  {
    "ContainingType": "Oracap_App_API.Controllers.ViewTypesController",
    "Method": "PutViewTypeModel",
    "RelativePath": "api/ViewTypes/{id}",
    "HttpMethod": "PUT",
    "IsController": true,
    "Order": 0,
    "Parameters": [
      {
        "Name": "id",
        "Type": "System.Int32",
        "IsRequired": true
      },
      {
        "Name": "viewTypeModel",
        "Type": "Oracap_App_API.Model.ViewTypeModel",
        "IsRequired": true
      }
    ],
    "ReturnTypes": []
  },
  {
    "ContainingType": "Oracap_App_API.Controllers.ViewTypesController",
    "Method": "DeleteViewTypeModel",
    "RelativePath": "api/ViewTypes/{id}",
    "HttpMethod": "DELETE",
    "IsController": true,
    "Order": 0,
    "Parameters": [
      {
        "Name": "id",
        "Type": "System.Int32",
        "IsRequired": true
      }
    ],
    "ReturnTypes": []
  }
]